README.rst
setup.py
stockton/__init__.py
stockton/__main__.py
stockton/cli.py
stockton/dns.py
stockton/geo.py
stockton/path.py
stockton.egg-info/PKG-INFO
stockton.egg-info/SOURCES.txt
stockton.egg-info/dependency_links.txt
stockton.egg-info/entry_points.txt
stockton.egg-info/requires.txt
stockton.egg-info/top_level.txt
stockton/concur/__init__.py
stockton/concur/formats/__init__.py
stockton/concur/formats/base.py
stockton/concur/formats/generic.py
stockton/concur/formats/opendkim.py
stockton/concur/formats/postfix.py
stockton/concur/formats/spamassassin.py
stockton/interface/__init__.py
stockton/interface/base.py
stockton/interface/dkim.py
stockton/interface/postfix.py
stockton/interface/smtp.py
stockton/interface/spam.py
stockton/interface/srs.py
tests/__init__.py
tests/cli_test.py
tests/concur_test.py
tests/dns_test.py
tests/geo_test.py
tests/interface_test.py
tests/main_test.py
tests/path_test.py