Metadata-Version: 1.1
Name: stockton
Version: 0.0.4
Summary: Easy peasy email forwarding for a custom domain
Home-page: http://github.com/jaymon/stockton
Author: Jay Marcyes
Author-email: jay@marcyes.com
License: GPLv2+
Platform: UNKNOWN
Classifier: Development Status :: 4 - Beta
Classifier: Environment :: Web Environment
Classifier: Intended Audience :: End Users/Desktop
Classifier: Operating System :: POSIX :: Linux
Classifier: Programming Language :: Python :: 2.7
Classifier: Topic :: Communications :: Email
Classifier: License :: OSI Approved :: GNU General Public License v2 or later (GPLv2+)
